{
    "key": "group_670e69f5a3a3f",
    "title": "Block: Service Reviews",
    "fields": [
        {
            "key": "field_671664ef81011",
            "label": "Reviews title",
            "name": "reviews_title",
            "aria-label": "",
            "type": "text",
            "instructions": "",
            "required": 0,
            "conditional_logic": 0,
            "wrapper": {
                "width": "",
                "class": "",
                "id": ""
            },
            "default_value": "",
            "maxlength": "",
            "allow_in_bindings": 0,
            "placeholder": "",
            "prepend": "",
            "append": ""
        },
        {
            "key": "field_671664fe81012",
            "label": "Reviews description",
            "name": "reviews_description",
            "aria-label": "",
            "type": "textarea",
            "instructions": "",
            "required": 0,
            "conditional_logic": 0,
            "wrapper": {
                "width": "",
                "class": "",
                "id": ""
            },
            "default_value": "",
            "acfe_textarea_code": 0,
            "maxlength": "",
            "allow_in_bindings": 0,
            "rows": "",
            "placeholder": "",
            "new_lines": ""
        },
        {
            "key": "field_6716607946080",
            "label": "Reviews posts",
            "name": "reviews_items",
            "aria-label": "",
            "type": "relationship",
            "instructions": "",
            "required": 0,
            "conditional_logic": 0,
            "wrapper": {
                "width": "",
                "class": "",
                "id": ""
            },
            "post_type": [
                "reviews"
            ],
            "post_status": "",
            "taxonomy": "",
            "filters": [
                "search"
            ],
            "return_format": "object",
            "acfe_bidirectional": {
                "acfe_bidirectional_enabled": "0"
            },
            "min": "",
            "max": "",
            "allow_in_bindings": 0,
            "elements": "",
            "bidirectional": 0,
            "bidirectional_target": []
        }
    ],
    "location": [
        [
            {
                "param": "block",
                "operator": "==",
                "value": "acf\/single-service-rewiews"
            }
        ]
    ],
    "menu_order": 0,
    "position": "normal",
    "style": "default",
    "label_placement": "left",
    "instruction_placement": "label",
    "hide_on_screen": "",
    "active": true,
    "description": "",
    "show_in_rest": 0,
    "acfe_display_title": "",
    "acfe_autosync": [
        "json"
    ],
    "acfe_form": 0,
    "acfe_meta": "",
    "acfe_note": "",
    "modified": 1729520972
}
